setup.py
bin/jokeByScript
pyutility/__init__.py
pyutility/command_line.py
pyutility/text.py
pyutility/utils.py
pyutility.egg-info/PKG-INFO
pyutility.egg-info/SOURCES.txt
pyutility.egg-info/dependency_links.txt
pyutility.egg-info/entry_points.txt
pyutility.egg-info/not-zip-safe
pyutility.egg-info/top_level.txt