Metadata-Version: 1.0
Name: pyutility
Version: 0.0.1
Summary: Some utility functions for data manipulation
Home-page: https://github.com/nickytong/pyutility
Author: nickytong
Author-email: ptong1@mdanderson.org
License: MIT
Platform: UNKNOWN
